kubefox_sdk/__init__.py
kubefox_sdk/const.py
kubefox_sdk/kubefox_pb2.py
kubefox_sdk/kubefox_pb2_grpc.py
kubefox_sdk/sdk.py
kubefox_sdk-0.4.1.dist-info/LICENSE
kubefox_sdk-0.4.1.dist-info/METADATA
kubefox_sdk-0.4.1.dist-info/WHEEL
kubefox_sdk-0.4.1.dist-info/top_level.txt
kubefox_sdk-0.4.1.dist-info/RECORD
