Metadata-Version: 2.1
Name: kubefox-sdk
Version: 0.4.1
Summary: Software development kit for KubeFox
Author: John Long
Author-email: john.long@xigxog.io
Maintainer: XigXog
Maintainer-email: info@xigxog.io
License: Apache License 2.0
Classifier: Intended Audience :: Developers
Classifier: Programming Language :: Python :: 3
Classifier: Topic :: Software Development
Requires-Python: >=3.9
License-File: LICENSE
Requires-Dist: grpcio
Requires-Dist: prometheus-client
Requires-Dist: protobuf
Requires-Dist: structlog
